yara_grep/__init__.py
yara_grep/cli.py
yara_grep-0.5.0.dist-info/entry_points.txt
yara_grep-0.5.0.dist-info/METADATA
yara_grep-0.5.0.dist-info/WHEEL
yara_grep-0.5.0.dist-info/RECORD
