Metadata-Version: 2.1
Name: yara-grep
Version: 0.5.0
Summary: CLI tool for rapid Yara rule prototyping
Home-page: https://github.com/0xa13d/yara-grep
Author: Aled Mason
Author-email: aledmason@microsoft.com
Requires-Python: >=3.10,<4.0
Classifier: Programming Language :: Python :: 3
Classifier: Programming Language :: Python :: 3.10
Classifier: Programming Language :: Python :: 3.11
Classifier: Programming Language :: Python :: 3.12
Requires-Dist: tabulate (>=0.9.0,<0.10.0)
Requires-Dist: yara-python (>=4.5.1,<5.0.0)
Project-URL: Repository, https://github.com/0xa13d/yara-grep
